{"client":"Thunder Client","collectionName":"valex","dateExported":"2022-09-05T14:35:44.326Z","version":"1.1","folders":[],"requests":[{"_id":"6575e96c-a95c-4a46-b7aa-dbb618f460ee","colId":"87ca9245-7b4d-4d44-bac6-e672994e616a","containerId":"","name":"create-card","url":"localhost:4000/new-card","method":"POST","sortNum":10000,"created":"2022-09-03T00:03:14.788Z","modified":"2022-09-05T12:45:16.340Z","headers":[{"name":"x-api-key","value":"zadKLNx.DzvOVjQH01TumGl2urPjPQSxUbf67vs0"}],"params":[],"body":{"type":"json","raw":"{\n  \"employeeId\": 3,\n  \"type\": \"health\"\n}","form":[]},"tests":[]},{"_id":"887cf8d1-adeb-423f-97d4-8de1ac016230","colId":"87ca9245-7b4d-4d44-bac6-e672994e616a","containerId":"","name":"activate-card","url":"localhost:4000/new-card/12","method":"POST","sortNum":20000,"created":"2022-09-04T07:39:54.127Z","modified":"2022-09-05T12:47:17.954Z","headers":[],"params":[],"body":{"type":"json","raw":"{\n  \"cvv\": \"718\",\n  \"password\": \"1234\"\n}","form":[]},"tests":[]},{"_id":"3b2e36df-f1e2-4589-a338-cf17f5ff9048","colId":"87ca9245-7b4d-4d44-bac6-e672994e616a","containerId":"","name":"extract","url":"localhost:4000/card/11","method":"GET","sortNum":40000,"created":"2022-09-04T10:28:50.677Z","modified":"2022-09-05T12:45:51.305Z","headers":[],"params":[],"tests":[]},{"_id":"d592f60b-cc17-43ec-98f7-75d6e0477dbf","colId":"87ca9245-7b4d-4d44-bac6-e672994e616a","containerId":"","name":"lock-card","url":"localhost:4000/card/12/lock","method":"POST","sortNum":50000,"created":"2022-09-05T10:53:46.856Z","modified":"2022-09-05T12:46:33.965Z","headers":[],"params":[],"body":{"type":"json","raw":"{\n  \"password\": \"1234\"\n}","form":[]},"tests":[]},{"_id":"dadc8153-be08-4807-ba0f-8305f8eb2a9b","colId":"87ca9245-7b4d-4d44-bac6-e672994e616a","containerId":"","name":"unlock-card","url":"localhost:4000/card/12/unlock","method":"POST","sortNum":60000,"created":"2022-09-05T11:40:20.540Z","modified":"2022-09-05T12:47:41.937Z","headers":[],"params":[],"body":{"type":"json","raw":"{\n  \"password\": \"1234\"\n}","form":[]},"tests":[]},{"_id":"70ab46e6-cc7c-4fab-aec7-f3f4a336de31","colId":"87ca9245-7b4d-4d44-bac6-e672994e616a","containerId":"","name":"recharge","url":"localhost:4000/recharge/9","method":"POST","sortNum":70000,"created":"2022-09-05T11:50:07.864Z","modified":"2022-09-05T13:45:55.959Z","headers":[{"name":"x-api-key","value":"zadKLNx.DzvOVjQH01TumGl2urPjPQSxUbf67vs0"}],"params":[],"body":{"type":"json","raw":"{\n  \"amount\": \"5000\"\n}","form":[]},"tests":[]},{"_id":"84fc5e04-ba29-4d1b-a556-6d319a192632","colId":"87ca9245-7b4d-4d44-bac6-e672994e616a","containerId":"","name":"purchase","url":"localhost:4000/purchase/9","method":"POST","sortNum":80000,"created":"2022-09-05T12:49:01.546Z","modified":"2022-09-05T14:08:00.956Z","headers":[],"params":[],"body":{"type":"json","raw":"{\n  \"password\": \"1234\",\n  \"companyId\": 1,\n  \"amount\": \"2000\"\n}","form":[]},"tests":[]},{"_id":"e5d3cb9c-7686-4969-a0b7-3e28eb0f2b2c","colId":"87ca9245-7b4d-4d44-bac6-e672994e616a","containerId":"","name":"online-purchase","url":"localhost:4000/online-purchase","method":"POST","sortNum":90000,"created":"2022-09-05T13:54:03.096Z","modified":"2022-09-05T14:34:10.334Z","headers":[],"params":[],"body":{"type":"json","raw":"{\n  \"number\": \"6454-6273-7078-5173-2391\",\n  \"cardholderName\": \"CLEUZA C S GADOLFINI\",\n  \"expirationDate\": \"09/27\",\n  \"securityCode\": \"626\",\n  \"companyId\": 1,\n  \"amount\": 10000\n}","form":[]},"tests":[]}],"settings":{}}
